optiqs/__init__.py
optiqs/stokes_formalism.py
optiqs-0.0.2.dist-info/METADATA
optiqs-0.0.2.dist-info/WHEEL
optiqs-0.0.2.dist-info/licenses/LICENSE
optiqs-0.0.2.dist-info/RECORD
