Metadata-Version: 2.1
Name: optiQs
Version: 0.0.2
Summary: Simulation of quantum optic elements
Project-URL: Homepage, https://github.com/SammithSB/qwanta
Project-URL: Bug Tracker, https://github.com/SammithSB/qwanta/issues
Author-email: Sammith S Bharadwaj <sammithsb@gmail.com>
License: MIT License
Classifier: License :: OSI Approved :: MIT License
Classifier: Operating System :: OS Independent
Classifier: Programming Language :: Python :: 3
Requires-Python: >=3.7
